successfactors_auth/__init__.py
successfactors_auth/auth.py
successfactors_auth/templates/sf_saml_template.xml
successfactors_auth-0.0.10.dist-info/METADATA
successfactors_auth-0.0.10.dist-info/WHEEL
successfactors_auth-0.0.10.dist-info/licenses/LICENSE
successfactors_auth-0.0.10.dist-info/RECORD
