Metadata-Version: 2.1
Name: successfactors-auth
Version: 0.0.10
Summary: Authenticate to the SuccessFactors API.
Project-URL: Homepage, https://github.com/skoobasteeve/successfactors_auth
Project-URL: Bug Tracker, https://github.com/skoobasteeve/successfactors_auth/issues
Author-email: Ray Lyon <ray@raylyon.net>
License-File: LICENSE
Classifier: License :: OSI Approved :: Apache Software License
Classifier: Operating System :: OS Independent
Classifier: Programming Language :: Python :: 3
Requires-Python: >=3.9
Requires-Dist: lxml
Requires-Dist: requests
Requires-Dist: xmlsec
